{
    "GNN_basis": {
        "MODEL_NAME": "GNN_basis",
        "MODEL_WRAPER": "model_wraper_gnn",
        "PATH_TRAIN": "/gpfs/data/fs72150/springerd/Projects/LuttingerWard_from_ML/data/SigmaTrans/U2c0_b30_N250000.hdf5",
        "TRAINDATA": "metiso/data/30.0",
        "VALIDATIONDATA": "transprox/data/30.0",
        "SPLIT": 0.8,
        "DATA_LOADER": "Dataset_graph_generic",

        "continue": false,
        "SAVEPATH": "",

        "n_nodes":                  300,
        "weird":                    false,
        "batch_size":               1,
        "learning_rate":            1e-4,
        "weight_decay":             1e-7,
        "epochs":                   20,

        "omega_steps":              300,
        "tau_steps":                300,
        "out_dim":                  300,
        "message_in_dim":           1800,
        "message_hidden_dim":       200,
        "message_out_dim":          300,
        "update_hidden_dim":        200,
        "update_in_dim":            1500,
        "update_out_dim":           900,
        "pre_pool_hidden_dim":      200,
        "pre_pool_out_dim":         200,
        "post_pool_hidden_dim":     200,
        "nr_coefficients":          300,
        "hidden_layer":             4,

        "device_type": "gpu",
        "devices": 2,
        "num_nodes": 1
    }
}
